a_sync/ENVIRONMENT_VARIABLES.py
a_sync/__init__.pxd
a_sync/__init__.py
a_sync/_smart.c
a_sync/_smart.cpython-310-i386-linux-gnu.so
a_sync/_smart.pxd
a_sync/_smart.pyi
a_sync/_smart.pyx
a_sync/_typing.py
a_sync/aliases.py
a_sync/debugging.c
a_sync/debugging.cpython-310-i386-linux-gnu.so
a_sync/debugging.pyi
a_sync/debugging.pyx
a_sync/exceptions.c
a_sync/exceptions.cpython-310-i386-linux-gnu.so
a_sync/exceptions.pyi
a_sync/exceptions.pyx
a_sync/executor.py
a_sync/functools.c
a_sync/functools.cpython-310-i386-linux-gnu.so
a_sync/functools.pxd
a_sync/functools.pyi
a_sync/functools.pyx
a_sync/future.py
a_sync/iter.c
a_sync/iter.cpython-310-i386-linux-gnu.so
a_sync/iter.pxd
a_sync/iter.pyi
a_sync/iter.pyx
a_sync/py.typed
a_sync/task.py
a_sync/a_sync/__init__.py
a_sync/a_sync/_descriptor.c
a_sync/a_sync/_descriptor.cpython-310-i386-linux-gnu.so
a_sync/a_sync/_descriptor.pyi
a_sync/a_sync/_descriptor.pyx
a_sync/a_sync/_flags.c
a_sync/a_sync/_flags.cpython-310-i386-linux-gnu.so
a_sync/a_sync/_flags.pxd
a_sync/a_sync/_flags.pyx
a_sync/a_sync/_helpers.c
a_sync/a_sync/_helpers.cpython-310-i386-linux-gnu.so
a_sync/a_sync/_helpers.pxd
a_sync/a_sync/_helpers.pyi
a_sync/a_sync/_helpers.pyx
a_sync/a_sync/_kwargs.c
a_sync/a_sync/_kwargs.cpython-310-i386-linux-gnu.so
a_sync/a_sync/_kwargs.pxd
a_sync/a_sync/_kwargs.pyx
a_sync/a_sync/_meta.py
a_sync/a_sync/abstract.c
a_sync/a_sync/abstract.cpython-310-i386-linux-gnu.so
a_sync/a_sync/abstract.pyi
a_sync/a_sync/abstract.pyx
a_sync/a_sync/base.c
a_sync/a_sync/base.cpython-310-i386-linux-gnu.so
a_sync/a_sync/base.pyi
a_sync/a_sync/base.pyx
a_sync/a_sync/config.py
a_sync/a_sync/decorator.py
a_sync/a_sync/flags.c
a_sync/a_sync/flags.cpython-310-i386-linux-gnu.so
a_sync/a_sync/flags.pxd
a_sync/a_sync/flags.pyi
a_sync/a_sync/flags.pyx
a_sync/a_sync/function.c
a_sync/a_sync/function.cpython-310-i386-linux-gnu.so
a_sync/a_sync/function.pxd
a_sync/a_sync/function.pyi
ez_a_sync-0.33.13.dist-info/METADATA
ez_a_sync-0.33.13.dist-info/WHEEL
ez_a_sync-0.33.13.dist-info/top_level.txt
ez_a_sync-0.33.13.dist-info/RECORD
ez_a_sync-0.33.13.dist-info/licenses/LICENSE.txt
