Metadata-Version: 2.4
Name: ez_a_sync
Version: 0.33.13
Summary: A library that makes it easy to define objects that can be used for both sync and async use cases.
Home-page: https://github.com/BobTheBuidler/a-sync
Author: BobTheBuidler
Author-email: bobthebuidlerdefi@gmail.com
License: MIT
Classifier: Intended Audience :: Developers
Classifier: Programming Language :: Python :: 3
Classifier: Programming Language :: Python :: 3 :: Only
Classifier: Programming Language :: Python :: 3.10
Classifier: Programming Language :: Python :: 3.11
Classifier: Programming Language :: Python :: 3.12
Classifier: Programming Language :: Python :: 3.13
Classifier: Programming Language :: Python :: 3.14
Classifier: Programming Language :: Python :: Implementation :: CPython
Classifier: Operating System :: OS Independent
Classifier: Topic :: Software Development :: Libraries
Requires-Python: >=3.10,<3.15
License-File: LICENSE.txt
Requires-Dist: aiolimiter>=1
Requires-Dist: async_lru_threadsafe==2.0.5
Requires-Dist: async_property==0.2.2
Requires-Dist: typed_envs>=0.0.5
Requires-Dist: typing_extensions>=4.1.0
Dynamic: author
Dynamic: author-email
Dynamic: classifier
Dynamic: description
Dynamic: description-content-type
Dynamic: home-page
Dynamic: license
Dynamic: license-file
Dynamic: requires-dist
Dynamic: requires-python
Dynamic: summary
